fftresize
