Metadata-Version: 1.1
Name: FFTresize
Version: 1.0
Summary: FFTresize resizes images using zero-padding in the frequency
